rumi/__init__.py
rumi/base_reader.py
rumi/cache.py
rumi/version.py
rumi/file_rumi/__init__.py
rumi/file_rumi/reader.py
rumi/file_rumi/reporter.py
rumi/msg_rumi/__init__.py
rumi/msg_rumi/reader.py
rumi/msg_rumi/reporter.py
rumi_i18n-0.0.1a1.post2.data/data/requirements.txt
rumi_i18n-0.0.1a1.post2.dist-info/LICENSE
rumi_i18n-0.0.1a1.post2.dist-info/METADATA
rumi_i18n-0.0.1a1.post2.dist-info/WHEEL
rumi_i18n-0.0.1a1.post2.dist-info/top_level.txt
rumi_i18n-0.0.1a1.post2.dist-info/RECORD
