Metadata-Version: 2.1
Name: rumi-i18n
Version: 0.0.1a1.post2
Summary: A static site translation monitoring tool
Home-page: https://github.com/rotationalio/rumi
Author: Tianshu Li
Author-email: tianshu@rotational.io
Maintainer: Tianshu Li
Maintainer-email: tianshu@rotational.io
License: Apache
Download-URL: https://github.com/rotationalio/rumi/tarball/v0.0.1a1.post2
Keywords: rumi,python,translation monitoring,l10n
Platform: UNKNOWN
Classifier: Development Status :: 4 - Beta
Classifier: Environment :: Console
Classifier: License :: OSI Approved :: Apache Software License
Classifier: Natural Language :: English
Classifier: Operating System :: OS Independent
Classifier: Programming Language :: Python :: 3
License-File: LICENSE
Requires-Dist: GitPython (==3.1.24)
Requires-Dist: tabulate (==0.8.9)
Requires-Dist: pandas (==1.3.0)
Requires-Dist: pytest (==6.2.5)
